udlai/__init__.py
udlai/_version.py
udlai/feature_api.py
udlai/geocoding_api.py
udlai/tests/__init__.py
udlai/tests/test_feature_api.py
udlai/tests/test_geocoding.py
udlai-0.6.0.dist-info/licenses/LICENSE
udlai-0.6.0.dist-info/METADATA
udlai-0.6.0.dist-info/WHEEL
udlai-0.6.0.dist-info/top_level.txt
udlai-0.6.0.dist-info/RECORD
