Metadata-Version: 2.4
Name: udlai
Version: 0.6.0
Summary: UDL.AI Python interface
Home-page: https://github.com/udl-ai/udlai
Author: Martin Fleischmann
Author-email: m.fleischmann@urbandatalab.net
Requires-Python: >=3.8
License-File: LICENSE
Requires-Dist: requests
Requires-Dist: pandas
Dynamic: author
Dynamic: author-email
Dynamic: description
Dynamic: description-content-type
Dynamic: home-page
Dynamic: license-file
Dynamic: requires-dist
Dynamic: requires-python
Dynamic: summary
